falderal/__init__.py
falderal/driver.py
falderal/objects.py
falderal/tests.py
Falderal-0.14.dist-info/LICENSE
Falderal-0.14.dist-info/METADATA
Falderal-0.14.dist-info/WHEEL
Falderal-0.14.dist-info/entry_points.txt
Falderal-0.14.dist-info/top_level.txt
Falderal-0.14.dist-info/RECORD
