Metadata-Version: 2.1
Name: Falderal
Version: 0.14
Summary: Falderal: literate testing for programming languages
Author-email: Chris Pressey <packages@catseye.tc>
License: BSD 3-Clause License        
Project-URL: website, https://catseye.tc/node/Falderal
Classifier: License :: OSI Approved :: BSD License
Classifier: Operating System :: OS Independent
Classifier: Programming Language :: Python :: 2.7
Classifier: Programming Language :: Python :: 3
Classifier: Topic :: Software Development :: Testing
Requires-Python: >=2.7,>=3.5
License-File: LICENSE
